{
  "id": "EAG047",
  "code": "EAG047",
  "name": "許英欽",
  "photo": "https://lh3.googleusercontent.com/pw/AP1GczM0xkDG0fG3clA0QeIUXyfAkEGDTNtOIp4CnqcOjapoINdYOGs9pCX3DaifB7GJ0Hv2ScLhd9JAPY1M9b8ZPheZmu8Lq2AcU5TybQwZC2pRn5uDo-r3Yh4WaX4xkol1ncKiewUhygHA9jhgdS1co5g=w310-h335-no",
  "career": {
    "debut": 2015,
    "teams": [
      "火把老鷹"
    ],
    "totalSeasons": 11
  },
  "seasons": [
    {
      "year": 2025,
      "team": "火把老鷹",
      "number": "12",
      "batting": {
        "games": 7,
        "pa": 12,
        "ab": 11,
        "hits": 2,
        "singles": 2,
        "doubles": 0,
        "triples": 0,
        "hr": 0,
        "rbi": 2,
        "runs": 2,
        "bb": 0,
        "so": 6,
        "sb": 0,
        "sf": 0,
        "totalBases": 2
      },
      "pitching": null,
      "pitchingCalculated": null,
      "rankings": {
        "rc": 526,
        "hits": 411,
        "hr": 1197,
        "rbi": 337,
        "avg": 1124,
        "w": 475,
        "sv": 423,
        "so": 642,
        "era": 1124,
        "whip": 1124,
        "fip": 0
      }
    },
    {
      "year": 2024,
      "team": "火把老鷹",
      "number": "12",
      "batting": {
        "games": 7,
        "pa": 12,
        "ab": 8,
        "hits": 5,
        "singles": 5,
        "doubles": 0,
        "triples": 0,
        "hr": 0,
        "rbi": 1,
        "runs": 3,
        "bb": 0,
        "so": 1,
        "sb": 1,
        "sf": 0,
        "totalBases": 5
      },
      "pitching": null,
      "pitchingCalculated": null,
      "rankings": {
        "rc": 95,
        "hits": 123,
        "hr": 1169,
        "rbi": 317,
        "avg": 903,
        "w": 484,
        "sv": 454,
        "so": 576,
        "era": 903,
        "whip": 903,
        "fip": 0
      }
    },
    {
      "year": 2023,
      "team": "火把老鷹",
      "number": "12",
      "batting": {
        "games": 5,
        "pa": 11,
        "ab": 8,
        "hits": 1,
        "singles": 1,
        "doubles": 0,
        "triples": 0,
        "hr": 0,
        "rbi": 1,
        "runs": 1,
        "bb": 0,
        "so": 5,
        "sb": 0,
        "sf": 0,
        "totalBases": 1
      },
      "pitching": null,
      "pitchingCalculated": null,
      "rankings": {
        "rc": 317,
        "hits": 378,
        "hr": 1158,
        "rbi": 309,
        "avg": 896,
        "w": 355,
        "sv": 326,
        "so": 443,
        "era": 896,
        "whip": 896,
        "fip": 0
      }
    },
    {
      "year": 2022,
      "team": "火把老鷹",
      "number": "12",
      "batting": {
        "games": 0,
        "pa": 0,
        "ab": 0,
        "hits": 0,
        "singles": 0,
        "doubles": 0,
        "triples": 0,
        "hr": 0,
        "rbi": 0,
        "runs": 0,
        "bb": 0,
        "so": 0,
        "sb": 0,
        "sf": 0,
        "totalBases": 0
      },
      "pitching": null,
      "pitchingCalculated": null,
      "rankings": {
        "rc": 655,
        "hits": 614,
        "hr": 162,
        "rbi": 527,
        "avg": 943,
        "w": 359,
        "sv": 319,
        "so": 470,
        "era": 943,
        "whip": 943,
        "fip": 0
      }
    },
    {
      "year": 2021,
      "team": "火把老鷹",
      "number": "12",
      "batting": {
        "games": 0,
        "pa": 0,
        "ab": 0,
        "hits": 0,
        "singles": 0,
        "doubles": 0,
        "triples": 0,
        "hr": 0,
        "rbi": 0,
        "runs": 0,
        "bb": 0,
        "so": 0,
        "sb": 0,
        "sf": 0,
        "totalBases": 0
      },
      "pitching": null,
      "pitchingCalculated": null,
      "rankings": {
        "rc": 736,
        "hits": 694,
        "hr": 147,
        "rbi": 628,
        "avg": 1022,
        "w": 392,
        "sv": 335,
        "so": 522,
        "era": 1022,
        "whip": 1022,
        "fip": 0
      }
    },
    {
      "year": 2020,
      "team": "火把老鷹",
      "number": "12",
      "batting": {
        "games": 9,
        "pa": 32,
        "ab": 25,
        "hits": 5,
        "singles": 5,
        "doubles": 0,
        "triples": 0,
        "hr": 0,
        "rbi": 6,
        "runs": 6,
        "bb": 0,
        "so": 6,
        "sb": 0,
        "sf": 0,
        "totalBases": 5
      },
      "pitching": null,
      "pitchingCalculated": null,
      "rankings": {
        "rc": 287,
        "hits": 311,
        "hr": 1487,
        "rbi": 166,
        "avg": 1101,
        "w": 493,
        "sv": 434,
        "so": 635,
        "era": 1101,
        "whip": 1101,
        "fip": 0
      }
    },
    {
      "year": 2019,
      "team": "火把老鷹",
      "number": "12",
      "batting": {
        "games": 6,
        "pa": 14,
        "ab": 11,
        "hits": 2,
        "singles": 2,
        "doubles": 0,
        "triples": 0,
        "hr": 0,
        "rbi": 2,
        "runs": 3,
        "bb": 0,
        "so": 4,
        "sb": 0,
        "sf": 0,
        "totalBases": 2
      },
      "pitching": null,
      "pitchingCalculated": null,
      "rankings": {
        "rc": 416,
        "hits": 449,
        "hr": 1340,
        "rbi": 349,
        "avg": 917,
        "w": 271,
        "sv": 237,
        "so": 407,
        "era": 917,
        "whip": 917,
        "fip": 0
      }
    },
    {
      "year": 2018,
      "team": "火把老鷹",
      "number": "12",
      "batting": {
        "games": 11,
        "pa": 27,
        "ab": 20,
        "hits": 8,
        "singles": 8,
        "doubles": 0,
        "triples": 0,
        "hr": 0,
        "rbi": 6,
        "runs": 4,
        "bb": 0,
        "so": 2,
        "sb": 0,
        "sf": 0,
        "totalBases": 8
      },
      "pitching": null,
      "pitchingCalculated": null,
      "rankings": {
        "rc": 181,
        "hits": 195,
        "hr": 1471,
        "rbi": 166,
        "avg": 940,
        "w": 324,
        "sv": 271,
        "so": 435,
        "era": 940,
        "whip": 940,
        "fip": 0
      }
    },
    {
      "year": 2017,
      "team": "火把老鷹",
      "number": "EAG047",
      "batting": {
        "games": 15,
        "pa": 45,
        "ab": 34,
        "hits": 8,
        "singles": 8,
        "doubles": 0,
        "triples": 0,
        "hr": 0,
        "rbi": 7,
        "runs": 9,
        "bb": 0,
        "so": 8,
        "sb": 2,
        "sf": 0,
        "totalBases": 8
      },
      "pitching": null,
      "pitchingCalculated": null,
      "rankings": {
        "rc": 213,
        "hits": 233,
        "hr": 915,
        "rbi": 188,
        "avg": 340,
        "w": 0,
        "sv": 0,
        "so": 0,
        "era": 0,
        "whip": 0,
        "fip": 0
      }
    },
    {
      "year": 2016,
      "team": "火把老鷹",
      "number": "EAG047",
      "batting": {
        "games": 18,
        "pa": 50,
        "ab": 39,
        "hits": 11,
        "singles": 9,
        "doubles": 2,
        "triples": 0,
        "hr": 0,
        "rbi": 9,
        "runs": 9,
        "bb": 0,
        "so": 11,
        "sb": 1,
        "sf": 1,
        "totalBases": 13
      },
      "pitching": null,
      "pitchingCalculated": null,
      "rankings": {
        "rc": 186,
        "hits": 162,
        "hr": 868,
        "rbi": 148,
        "avg": 105,
        "w": 0,
        "sv": 0,
        "so": 0,
        "era": 0,
        "whip": 0,
        "fip": 0
      }
    },
    {
      "year": 2015,
      "team": "火把老鷹",
      "number": "EAG047",
      "batting": {
        "games": 9,
        "pa": 21,
        "ab": 18,
        "hits": 0,
        "singles": 0,
        "doubles": 0,
        "triples": 0,
        "hr": 0,
        "rbi": 3,
        "runs": 6,
        "bb": 0,
        "so": 10,
        "sb": 0,
        "sf": 0,
        "totalBases": 0
      },
      "pitching": null,
      "pitchingCalculated": null,
      "rankings": {
        "rc": 901,
        "hits": 903,
        "hr": 655,
        "rbi": 313,
        "avg": 624,
        "w": 0,
        "sv": 0,
        "so": 0,
        "era": 0,
        "whip": 0,
        "fip": 0
      }
    }
  ]
}