{
  "id": "EAG116",
  "code": "EAG116",
  "name": "李明澤",
  "photo": "",
  "career": {
    "debut": 2022,
    "teams": [
      "火把老鷹"
    ],
    "totalSeasons": 2
  },
  "seasons": [
    {
      "year": 2023,
      "team": "火把老鷹",
      "number": "103",
      "batting": {
        "games": 1,
        "pa": 3,
        "ab": 3,
        "hits": 2,
        "singles": 2,
        "doubles": 0,
        "triples": 0,
        "hr": 0,
        "rbi": 0,
        "runs": 1,
        "bb": 0,
        "so": 0,
        "sb": 0,
        "sf": 0,
        "totalBases": 2
      },
      "rankings": {
        "rc": 278,
        "hits": 234,
        "hr": 977,
        "rbi": 1295,
        "avg": 896
      }
    },
    {
      "year": 2022,
      "team": "火把老鷹",
      "number": "22",
      "batting": {
        "games": 0,
        "pa": 0,
        "ab": 0,
        "hits": 0,
        "singles": 0,
        "doubles": 0,
        "triples": 0,
        "hr": 0,
        "rbi": 0,
        "runs": 0,
        "bb": 0,
        "so": 0,
        "sb": 0,
        "sf": 0,
        "totalBases": 0
      },
      "rankings": {
        "rc": 653,
        "hits": 612,
        "hr": 160,
        "rbi": 525,
        "avg": 943
      }
    }
  ]
}