{
  "id": "HUA084",
  "code": "HUA084",
  "name": "王澄葦",
  "photo": "https://lh3.googleusercontent.com/pw/AM-JKLUp09N2fczG1asRZ3lCN1zIeQUnpfOnCciUzpK0ap16gy7mOYePZ04siBodToIomaPycmf9-xhirF-AZpqGrIiEb7AZDaGCxQV0pFhSkcd0-9LS5RddnQphEVqUehqjQp4HKrsdQLiW_-8dnIvSvdeN=w310-h335-no",
  "career": {
    "debut": 2016,
    "teams": [
      "華江OB"
    ],
    "totalSeasons": 9
  },
  "seasons": [
    {
      "year": 2025,
      "team": "華江OB",
      "number": "6",
      "batting": {
        "games": 14,
        "pa": 59,
        "ab": 52,
        "hits": 21,
        "singles": 15,
        "doubles": 3,
        "triples": 2,
        "hr": 1,
        "rbi": 9,
        "runs": 21,
        "bb": 7,
        "so": 3,
        "sb": 0,
        "sf": 0,
        "totalBases": 31
      },
      "pitching": {
        "games": 1,
        "ip": 0.3333333333,
        "bf": 2,
        "so": 0,
        "bb": 1,
        "h": 0,
        "hr": 0,
        "r": 0,
        "er": 0,
        "w": 0,
        "l": 0,
        "sv": 0,
        "hld": 0,
        "cs": 0,
        "csAttempts": 0
      },
      "pitchingCalculated": {
        "era": 0,
        "whip": 3.0000000003,
        "fip": null,
        "kPer9": 0,
        "bbPer9": 27.000000002700002,
        "hPer9": 0,
        "csPercentage": 0
      },
      "rankings": {
        "rc": 26,
        "hits": 17,
        "hr": 28,
        "rbi": 95,
        "avg": 31,
        "w": 1347,
        "sv": 1295,
        "so": 1513,
        "era": 1124,
        "whip": 98,
        "fip": 0
      }
    },
    {
      "year": 2024,
      "team": "華江OB",
      "number": "6",
      "batting": {
        "games": 9,
        "pa": 37,
        "ab": 30,
        "hits": 11,
        "singles": 9,
        "doubles": 2,
        "triples": 0,
        "hr": 0,
        "rbi": 9,
        "runs": 5,
        "bb": 7,
        "so": 1,
        "sb": 0,
        "sf": 0,
        "totalBases": 13
      },
      "pitching": null,
      "pitchingCalculated": null,
      "rankings": {
        "rc": 37,
        "hits": 31,
        "hr": 1384,
        "rbi": 29,
        "avg": 44,
        "w": 700,
        "sv": 670,
        "so": 792,
        "era": 903,
        "whip": 903,
        "fip": 0
      }
    },
    {
      "year": 2023,
      "team": "華江OB",
      "number": "6",
      "batting": {
        "games": 4,
        "pa": 17,
        "ab": 13,
        "hits": 4,
        "singles": 3,
        "doubles": 1,
        "triples": 0,
        "hr": 0,
        "rbi": 3,
        "runs": 2,
        "bb": 3,
        "so": 1,
        "sb": 0,
        "sf": 1,
        "totalBases": 5
      },
      "pitching": null,
      "pitchingCalculated": null,
      "rankings": {
        "rc": 153,
        "hits": 156,
        "hr": 1260,
        "rbi": 156,
        "avg": 896,
        "w": 632,
        "sv": 603,
        "so": 720,
        "era": 896,
        "whip": 896,
        "fip": 0
      }
    },
    {
      "year": 2022,
      "team": "華江OB",
      "number": "6",
      "batting": {
        "games": 10,
        "pa": 47,
        "ab": 41,
        "hits": 20,
        "singles": 11,
        "doubles": 7,
        "triples": 2,
        "hr": 0,
        "rbi": 11,
        "runs": 21,
        "bb": 6,
        "so": 3,
        "sb": 1,
        "sf": 0,
        "totalBases": 31
      },
      "pitching": null,
      "pitchingCalculated": null,
      "rankings": {
        "rc": 4,
        "hits": 2,
        "hr": 1470,
        "rbi": 17,
        "avg": 12,
        "w": 654,
        "sv": 614,
        "so": 765,
        "era": 943,
        "whip": 943,
        "fip": 0
      }
    },
    {
      "year": 2021,
      "team": "華江OB",
      "number": "6",
      "batting": {
        "games": 8,
        "pa": 35,
        "ab": 32,
        "hits": 15,
        "singles": 9,
        "doubles": 4,
        "triples": 2,
        "hr": 0,
        "rbi": 13,
        "runs": 13,
        "bb": 3,
        "so": 5,
        "sb": 1,
        "sf": 0,
        "totalBases": 23
      },
      "pitching": null,
      "pitchingCalculated": null,
      "rankings": {
        "rc": 87,
        "hits": 74,
        "hr": 1544,
        "rbi": 49,
        "avg": 1022,
        "w": 696,
        "sv": 639,
        "so": 826,
        "era": 1022,
        "whip": 1022,
        "fip": 0
      }
    },
    {
      "year": 2019,
      "team": "華江OB",
      "number": "6",
      "batting": {
        "games": 0,
        "pa": 0,
        "ab": 0,
        "hits": 0,
        "singles": 0,
        "doubles": 0,
        "triples": 0,
        "hr": 0,
        "rbi": 0,
        "runs": 0,
        "bb": 0,
        "so": 0,
        "sb": 0,
        "sf": 0,
        "totalBases": 0
      },
      "pitching": null,
      "pitchingCalculated": null,
      "rankings": {
        "rc": 769,
        "hits": 739,
        "hr": 225,
        "rbi": 672,
        "avg": 917,
        "w": 565,
        "sv": 531,
        "so": 701,
        "era": 917,
        "whip": 917,
        "fip": 0
      }
    },
    {
      "year": 2018,
      "team": "華江OB",
      "number": "6",
      "batting": {
        "games": 0,
        "pa": 0,
        "ab": 0,
        "hits": 0,
        "singles": 0,
        "doubles": 0,
        "triples": 0,
        "hr": 0,
        "rbi": 0,
        "runs": 0,
        "bb": 0,
        "so": 0,
        "sb": 0,
        "sf": 0,
        "totalBases": 0
      },
      "pitching": null,
      "pitchingCalculated": null,
      "rankings": {
        "rc": 786,
        "hits": 768,
        "hr": 266,
        "rbi": 706,
        "avg": 940,
        "w": 603,
        "sv": 550,
        "so": 714,
        "era": 940,
        "whip": 940,
        "fip": 0
      }
    },
    {
      "year": 2017,
      "team": "華江OB",
      "number": "HUA084",
      "batting": {
        "games": 1,
        "pa": 5,
        "ab": 5,
        "hits": 3,
        "singles": 2,
        "doubles": 1,
        "triples": 0,
        "hr": 0,
        "rbi": 1,
        "runs": 2,
        "bb": 0,
        "so": 0,
        "sb": 1,
        "sf": 0,
        "totalBases": 4
      },
      "pitching": null,
      "pitchingCalculated": null,
      "rankings": {
        "rc": 338,
        "hits": 365,
        "hr": 539,
        "rbi": 455,
        "avg": 340,
        "w": 0,
        "sv": 0,
        "so": 0,
        "era": 0,
        "whip": 0,
        "fip": 0
      }
    },
    {
      "year": 2016,
      "team": "華江OB",
      "number": "HUA084",
      "batting": {
        "games": 1,
        "pa": 4,
        "ab": 4,
        "hits": 1,
        "singles": 0,
        "doubles": 1,
        "triples": 0,
        "hr": 0,
        "rbi": 0,
        "runs": 1,
        "bb": 0,
        "so": 1,
        "sb": 0,
        "sf": 0,
        "totalBases": 2
      },
      "pitching": null,
      "pitchingCalculated": null,
      "rankings": {
        "rc": 496,
        "hits": 502,
        "hr": 446,
        "rbi": 872,
        "avg": 349,
        "w": 0,
        "sv": 0,
        "so": 0,
        "era": 0,
        "whip": 0,
        "fip": 0
      }
    }
  ]
}