{
  "id": "NAN014",
  "code": "NAN014",
  "name": "林哲緯",
  "photo": "",
  "career": {
    "debut": 2011,
    "teams": [
      "南港高工OB",
      "ROOKIES"
    ],
    "totalSeasons": 4
  },
  "seasons": [
    {
      "year": 2014,
      "team": "南港高工OB",
      "number": "NAN014",
      "batting": {
        "games": 0,
        "pa": 0,
        "ab": 0,
        "hits": 0,
        "singles": 0,
        "doubles": 0,
        "triples": 0,
        "hr": 0,
        "rbi": 0,
        "runs": 0,
        "bb": 0,
        "so": 0,
        "sb": 0,
        "sf": 0,
        "totalBases": 0
      },
      "pitching": null,
      "pitchingCalculated": null,
      "rankings": {
        "rc": 529,
        "hits": 409,
        "hr": 27,
        "rbi": 378,
        "avg": 327,
        "w": 0,
        "sv": 0,
        "so": 0,
        "era": 0,
        "whip": 0,
        "fip": 0
      }
    },
    {
      "year": 2013,
      "team": "南港高工OB",
      "number": "NAN014",
      "batting": {
        "games": 0,
        "pa": 0,
        "ab": 0,
        "hits": 0,
        "singles": 0,
        "doubles": 0,
        "triples": 0,
        "hr": 0,
        "rbi": 0,
        "runs": 0,
        "bb": 0,
        "so": 0,
        "sb": 0,
        "sf": 0,
        "totalBases": 0
      },
      "pitching": null,
      "pitchingCalculated": null,
      "rankings": {
        "rc": 382,
        "hits": 322,
        "hr": 27,
        "rbi": 285,
        "avg": 323,
        "w": 0,
        "sv": 0,
        "so": 0,
        "era": 0,
        "whip": 0,
        "fip": 0
      }
    },
    {
      "year": 2012,
      "team": "ROOKIES",
      "number": "NAN014",
      "batting": {
        "games": 5,
        "pa": 19,
        "ab": 16,
        "hits": 2,
        "singles": 1,
        "doubles": 1,
        "triples": 0,
        "hr": 0,
        "rbi": 3,
        "runs": 4,
        "bb": 3,
        "so": 7,
        "sb": 1,
        "sf": 0,
        "totalBases": 3
      },
      "pitching": null,
      "pitchingCalculated": null,
      "rankings": {
        "rc": 195,
        "hits": 188,
        "hr": 238,
        "rbi": 134,
        "avg": 358,
        "w": 0,
        "sv": 0,
        "so": 0,
        "era": 0,
        "whip": 0,
        "fip": 0
      }
    },
    {
      "year": 2011,
      "team": "南港高工OB",
      "number": "NAN014",
      "batting": {
        "games": 2,
        "pa": 2,
        "ab": 1,
        "hits": 0,
        "singles": 0,
        "doubles": 0,
        "triples": 0,
        "hr": 0,
        "rbi": 0,
        "runs": 1,
        "bb": 1,
        "so": 1,
        "sb": 0,
        "sf": 0,
        "totalBases": 0
      },
      "pitching": null,
      "pitchingCalculated": null,
      "rankings": {
        "rc": 161,
        "hits": 208,
        "hr": 61,
        "rbi": 193,
        "avg": 450,
        "w": 0,
        "sv": 0,
        "so": 0,
        "era": 0,
        "whip": 0,
        "fip": 0
      }
    }
  ]
}