{
  "id": "NTP053",
  "code": "NTP053",
  "name": "賴奕翔",
  "photo": "",
  "career": {
    "debut": 2021,
    "teams": [
      "台北大學"
    ],
    "totalSeasons": 1
  },
  "seasons": [
    {
      "year": 2021,
      "team": "台北大學",
      "number": "52",
      "batting": {
        "games": 1,
        "pa": 4,
        "ab": 3,
        "hits": 0,
        "singles": 0,
        "doubles": 0,
        "triples": 0,
        "hr": 0,
        "rbi": 1,
        "runs": 1,
        "bb": 0,
        "so": 1,
        "sb": 0,
        "sf": 0,
        "totalBases": 0
      },
      "pitching": null,
      "pitchingCalculated": null,
      "rankings": {
        "rc": 599,
        "hits": 1618,
        "hr": 1095,
        "rbi": 420,
        "avg": 1022,
        "w": 160,
        "sv": 103,
        "so": 290,
        "era": 1022,
        "whip": 1022,
        "fip": 0
      }
    }
  ]
}