{
  "id": "NTU030",
  "code": "NTU030",
  "name": "高子鈞",
  "photo": "",
  "career": {
    "debut": 2013,
    "teams": [
      "台大化工OB"
    ],
    "totalSeasons": 4
  },
  "seasons": [
    {
      "year": 2016,
      "team": "台大化工OB",
      "number": "NTU030",
      "batting": {
        "games": 9,
        "pa": 41,
        "ab": 34,
        "hits": 12,
        "singles": 7,
        "doubles": 5,
        "triples": 0,
        "hr": 0,
        "rbi": 13,
        "runs": 15,
        "bb": 7,
        "so": 0,
        "sb": 3,
        "sf": 0,
        "totalBases": 17
      },
      "pitching": null,
      "pitchingCalculated": null,
      "rankings": {
        "rc": 121,
        "hits": 142,
        "hr": 823,
        "rbi": 73,
        "avg": 349,
        "w": 262,
        "sv": 227,
        "so": 384,
        "era": 119,
        "whip": 119,
        "fip": 0
      }
    },
    {
      "year": 2015,
      "team": "台大化工OB",
      "number": "NTU030",
      "batting": {
        "games": 15,
        "pa": 60,
        "ab": 54,
        "hits": 24,
        "singles": 18,
        "doubles": 3,
        "triples": 2,
        "hr": 1,
        "rbi": 21,
        "runs": 19,
        "bb": 3,
        "so": 4,
        "sb": 3,
        "sf": 3,
        "totalBases": 34
      },
      "pitching": {
        "games": 1,
        "ip": 2.333333333,
        "bf": 18,
        "so": 2,
        "bb": 2,
        "h": 6,
        "hr": 0,
        "r": 9,
        "er": 7,
        "w": 0,
        "l": 1,
        "sv": 0,
        "hld": 0,
        "cs": 1,
        "csAttempts": 7
      },
      "pitchingCalculated": {
        "era": 27.000000003857142,
        "whip": 3.428571429061224,
        "fip": null,
        "kPer9": 7.714285715387755,
        "bbPer9": 7.714285715387755,
        "hPer9": 23.142857146163266,
        "csPercentage": 0.14285714285714285
      },
      "rankings": {
        "rc": 39,
        "hits": 26,
        "hr": 45,
        "rbi": 13,
        "avg": 21,
        "w": 558,
        "sv": 512,
        "so": 159,
        "era": 130,
        "whip": 130,
        "fip": 0
      }
    },
    {
      "year": 2014,
      "team": "台大化工OB",
      "number": "NTU030",
      "batting": {
        "games": 9,
        "pa": 30,
        "ab": 28,
        "hits": 13,
        "singles": 10,
        "doubles": 2,
        "triples": 1,
        "hr": 0,
        "rbi": 6,
        "runs": 7,
        "bb": 1,
        "so": 1,
        "sb": 0,
        "sf": 1,
        "totalBases": 17
      },
      "pitching": {
        "games": 1,
        "ip": 2,
        "bf": 14,
        "so": 0,
        "bb": 3,
        "h": 5,
        "hr": 0,
        "r": 3,
        "er": 2,
        "w": 0,
        "l": 0,
        "sv": 0,
        "hld": 0,
        "cs": 2,
        "csAttempts": 7
      },
      "pitchingCalculated": {
        "era": 9,
        "whip": 4,
        "fip": null,
        "kPer9": 0,
        "bbPer9": 13.5,
        "hPer9": 22.5,
        "csPercentage": 0.2857142857142857
      },
      "rankings": {
        "rc": 103,
        "hits": 85,
        "hr": 533,
        "rbi": 138,
        "avg": 327,
        "w": 446,
        "sv": 409,
        "so": 508,
        "era": 115,
        "whip": 115,
        "fip": 0
      }
    },
    {
      "year": 2013,
      "team": "台大化工OB",
      "number": "NTU030",
      "batting": {
        "games": 10,
        "pa": 45,
        "ab": 44,
        "hits": 19,
        "singles": 11,
        "doubles": 8,
        "triples": 0,
        "hr": 0,
        "rbi": 17,
        "runs": 19,
        "bb": 0,
        "so": 4,
        "sb": 11,
        "sf": 1,
        "totalBases": 27
      },
      "pitching": {
        "games": 4,
        "ip": 8.666666667,
        "bf": 55,
        "so": 9,
        "bb": 14,
        "h": 9,
        "hr": 0,
        "r": 12,
        "er": 7,
        "w": 1,
        "l": 0,
        "sv": 0,
        "hld": 0,
        "cs": 0,
        "csAttempts": 8
      },
      "pitchingCalculated": {
        "era": 7.269230768951184,
        "whip": 2.653846153744083,
        "fip": null,
        "kPer9": 9.34615384579438,
        "bbPer9": 14.538461537902368,
        "hPer9": 9.34615384579438,
        "csPercentage": 0
      },
      "rankings": {
        "rc": 27,
        "hits": 24,
        "hr": 437,
        "rbi": 17,
        "avg": 323,
        "w": 37,
        "sv": 359,
        "so": 54,
        "era": 115,
        "whip": 115,
        "fip": 0
      }
    }
  ]
}