{
  "id": "ROO093",
  "code": "ROO093",
  "name": "凌子云",
  "photo": "https://lh3.googleusercontent.com/pw/AP1GczOV5OhQvgpD9TV0bQ2FFHUMNgCHrq8HcSYohiYSnpMfb7kgf5OQbaEPZ2jdnS7UdPOv81z_1WcI1CRC882aeGwshfBOBtHJbq7Yg5CFSP3vkaCd7wXPWOhpke9A4k7Z_VbH6wzEKDdzvKgV5X8OHyvW=w310-h335-no",
  "career": {
    "debut": 2024,
    "teams": [
      "Line Drive"
    ],
    "totalSeasons": 2
  },
  "seasons": [
    {
      "year": 2025,
      "team": "Line Drive",
      "number": "104",
      "batting": {
        "games": 0,
        "pa": 0,
        "ab": 0,
        "hits": 0,
        "singles": 0,
        "doubles": 0,
        "triples": 0,
        "hr": 0,
        "rbi": 0,
        "runs": 0,
        "bb": 0,
        "so": 0,
        "sb": 0,
        "sf": 0,
        "totalBases": 0
      },
      "pitching": null,
      "pitchingCalculated": null,
      "rankings": {
        "rc": 911,
        "hits": 809,
        "hr": 286,
        "rbi": 755,
        "avg": 1123,
        "w": 572,
        "sv": 522,
        "so": 739,
        "era": 1123,
        "whip": 1123,
        "fip": 0
      }
    },
    {
      "year": 2024,
      "team": "Line Drive",
      "number": "104",
      "batting": {
        "games": 0,
        "pa": 0,
        "ab": 0,
        "hits": 0,
        "singles": 0,
        "doubles": 0,
        "triples": 0,
        "hr": 0,
        "rbi": 0,
        "runs": 0,
        "bb": 0,
        "so": 0,
        "sb": 0,
        "sf": 0,
        "totalBases": 0
      },
      "pitching": null,
      "pitchingCalculated": null,
      "rankings": {
        "rc": 710,
        "hits": 672,
        "hr": 260,
        "rbi": 605,
        "avg": 903,
        "w": 605,
        "sv": 575,
        "so": 697,
        "era": 903,
        "whip": 903,
        "fip": 0
      }
    }
  ]
}