{
  "id": "TRO057",
  "code": "TRO057",
  "name": "簡子傑",
  "photo": "",
  "career": {
    "debut": 2020,
    "teams": [
      "楚奧特"
    ],
    "totalSeasons": 5
  },
  "seasons": [
    {
      "year": 2024,
      "team": "楚奧特",
      "number": "32",
      "batting": {
        "games": 0,
        "pa": 0,
        "ab": 0,
        "hits": 0,
        "singles": 0,
        "doubles": 0,
        "triples": 0,
        "hr": 0,
        "rbi": 0,
        "runs": 0,
        "bb": 0,
        "so": 0,
        "sb": 0,
        "sf": 0,
        "totalBases": 0
      },
      "rankings": {
        "rc": 573,
        "hits": 542,
        "hr": 130,
        "rbi": 475,
        "avg": 903
      }
    },
    {
      "year": 2023,
      "team": "楚奧特",
      "number": "34",
      "batting": {
        "games": 0,
        "pa": 0,
        "ab": 0,
        "hits": 0,
        "singles": 0,
        "doubles": 0,
        "triples": 0,
        "hr": 0,
        "rbi": 0,
        "runs": 0,
        "bb": 0,
        "so": 0,
        "sb": 0,
        "sf": 0,
        "totalBases": 0
      },
      "rankings": {
        "rc": 510,
        "hits": 461,
        "hr": 80,
        "rbi": 410,
        "avg": 896
      }
    },
    {
      "year": 2022,
      "team": "楚奧特",
      "number": "34",
      "batting": {
        "games": 0,
        "pa": 0,
        "ab": 0,
        "hits": 0,
        "singles": 0,
        "doubles": 0,
        "triples": 0,
        "hr": 0,
        "rbi": 0,
        "runs": 0,
        "bb": 0,
        "so": 0,
        "sb": 0,
        "sf": 0,
        "totalBases": 0
      },
      "rankings": {
        "rc": 575,
        "hits": 534,
        "hr": 82,
        "rbi": 447,
        "avg": 943
      }
    },
    {
      "year": 2021,
      "team": "楚奧特",
      "number": "34",
      "batting": {
        "games": 0,
        "pa": 0,
        "ab": 0,
        "hits": 0,
        "singles": 0,
        "doubles": 0,
        "triples": 0,
        "hr": 0,
        "rbi": 0,
        "runs": 0,
        "bb": 0,
        "so": 0,
        "sb": 0,
        "sf": 0,
        "totalBases": 0
      },
      "rankings": {
        "rc": 680,
        "hits": 638,
        "hr": 91,
        "rbi": 572,
        "avg": 1022
      }
    },
    {
      "year": 2020,
      "team": "楚奧特",
      "number": "34",
      "batting": {
        "games": 2,
        "pa": 9,
        "ab": 9,
        "hits": 6,
        "singles": 6,
        "doubles": 0,
        "triples": 0,
        "hr": 0,
        "rbi": 8,
        "runs": 4,
        "bb": 0,
        "so": 1,
        "sb": 0,
        "sf": 0,
        "totalBases": 6
      },
      "rankings": {
        "rc": 275,
        "hits": 250,
        "hr": 1217,
        "rbi": 109,
        "avg": 1101
      }
    }
  ]
}