{
  "id": "TRO011",
  "code": "TRO011",
  "name": "李瀚寧",
  "photo": "",
  "career": {
    "debut": 2016,
    "teams": [
      "楚奧特"
    ],
    "totalSeasons": 3
  },
  "seasons": [
    {
      "year": 2018,
      "team": "楚奧特",
      "number": "21",
      "batting": {
        "games": 0,
        "pa": 0,
        "ab": 0,
        "hits": 0,
        "singles": 0,
        "doubles": 0,
        "triples": 0,
        "hr": 0,
        "rbi": 0,
        "runs": 0,
        "bb": 0,
        "so": 0,
        "sb": 0,
        "sf": 0,
        "totalBases": 0
      },
      "pitching": null,
      "pitchingCalculated": null,
      "rankings": {
        "rc": 615,
        "hits": 597,
        "hr": 95,
        "rbi": 535,
        "avg": 940,
        "w": 206,
        "sv": 153,
        "so": 317,
        "era": 940,
        "whip": 940,
        "fip": 0
      }
    },
    {
      "year": 2017,
      "team": "楚奧特",
      "number": "TRO011",
      "batting": {
        "games": 2,
        "pa": 6,
        "ab": 6,
        "hits": 0,
        "singles": 0,
        "doubles": 0,
        "triples": 0,
        "hr": 0,
        "rbi": 0,
        "runs": 0,
        "bb": 0,
        "so": 2,
        "sb": 0,
        "sf": 0,
        "totalBases": 0
      },
      "pitching": null,
      "pitchingCalculated": null,
      "rankings": {
        "rc": 1004,
        "hits": 1005,
        "hr": 582,
        "rbi": 973,
        "avg": 340,
        "w": 0,
        "sv": 0,
        "so": 0,
        "era": 0,
        "whip": 0,
        "fip": 0
      }
    },
    {
      "year": 2016,
      "team": "楚奧特",
      "number": "TRO011",
      "batting": {
        "games": 3,
        "pa": 3,
        "ab": 3,
        "hits": 1,
        "singles": 1,
        "doubles": 0,
        "triples": 0,
        "hr": 0,
        "rbi": 0,
        "runs": 1,
        "bb": 0,
        "so": 1,
        "sb": 0,
        "sf": 0,
        "totalBases": 1
      },
      "pitching": null,
      "pitchingCalculated": null,
      "rankings": {
        "rc": 522,
        "hits": 490,
        "hr": 414,
        "rbi": 847,
        "avg": 349,
        "w": 0,
        "sv": 0,
        "so": 0,
        "era": 0,
        "whip": 0,
        "fip": 0
      }
    }
  ]
}