{
  "id": "YAN028",
  "code": "YAN028",
  "name": "呂紹弘",
  "photo": "",
  "career": {
    "debut": 2014,
    "teams": [
      "陽明OB"
    ],
    "totalSeasons": 6
  },
  "seasons": [
    {
      "year": 2019,
      "team": "陽明OB",
      "number": "88",
      "batting": {
        "games": 0,
        "pa": 0,
        "ab": 0,
        "hits": 0,
        "singles": 0,
        "doubles": 0,
        "triples": 0,
        "hr": 0,
        "rbi": 0,
        "runs": 0,
        "bb": 0,
        "so": 0,
        "sb": 0,
        "sf": 0,
        "totalBases": 0
      },
      "rankings": {
        "rc": 649,
        "hits": 619,
        "hr": 105,
        "rbi": 552,
        "avg": 917
      }
    },
    {
      "year": 2018,
      "team": "陽明OB",
      "number": "88",
      "batting": {
        "games": 0,
        "pa": 0,
        "ab": 0,
        "hits": 0,
        "singles": 0,
        "doubles": 0,
        "triples": 0,
        "hr": 0,
        "rbi": 0,
        "runs": 0,
        "bb": 0,
        "so": 0,
        "sb": 0,
        "sf": 0,
        "totalBases": 0
      },
      "rankings": {
        "rc": 667,
        "hits": 649,
        "hr": 147,
        "rbi": 587,
        "avg": 940
      }
    },
    {
      "year": 2017,
      "team": "陽明OB",
      "number": "YAN028",
      "batting": {
        "games": 0,
        "pa": 0,
        "ab": 0,
        "hits": 0,
        "singles": 0,
        "doubles": 0,
        "triples": 0,
        "hr": 0,
        "rbi": 0,
        "runs": 0,
        "bb": 0,
        "so": 0,
        "sb": 0,
        "sf": 0,
        "totalBases": 0
      },
      "rankings": {
        "rc": 687,
        "hits": 692,
        "hr": 186,
        "rbi": 636,
        "avg": 340
      }
    },
    {
      "year": 2016,
      "team": "陽明OB",
      "number": "YAN028",
      "batting": {
        "games": 0,
        "pa": 0,
        "ab": 0,
        "hits": 0,
        "singles": 0,
        "doubles": 0,
        "triples": 0,
        "hr": 0,
        "rbi": 0,
        "runs": 0,
        "bb": 0,
        "so": 0,
        "sb": 0,
        "sf": 0,
        "totalBases": 0
      },
      "rankings": {
        "rc": 665,
        "hits": 647,
        "hr": 146,
        "rbi": 593,
        "avg": 349
      }
    },
    {
      "year": 2015,
      "team": "陽明OB",
      "number": "YAN028",
      "batting": {
        "games": 1,
        "pa": 3,
        "ab": 2,
        "hits": 1,
        "singles": 1,
        "doubles": 0,
        "triples": 0,
        "hr": 0,
        "rbi": 0,
        "runs": 0,
        "bb": 0,
        "so": 1,
        "sb": 0,
        "sf": 0,
        "totalBases": 1
      },
      "rankings": {
        "rc": 435,
        "hits": 464,
        "hr": 400,
        "rbi": 808,
        "avg": 624
      }
    },
    {
      "year": 2014,
      "team": "陽明OB",
      "number": "YAN028",
      "batting": {
        "games": 7,
        "pa": 25,
        "ab": 19,
        "hits": 7,
        "singles": 4,
        "doubles": 3,
        "triples": 0,
        "hr": 0,
        "rbi": 7,
        "runs": 5,
        "bb": 1,
        "so": 4,
        "sb": 0,
        "sf": 1,
        "totalBases": 10
      },
      "rankings": {
        "rc": 147,
        "hits": 167,
        "hr": 492,
        "rbi": 106,
        "avg": 327
      }
    }
  ]
}